{
  "student_id": "1685",
  "concept_id": 3,
  "concept_text": "Prime Numbers and Prime Factors",
  "persona": {
    "description": "Student shows needs improvement of 'Prime Numbers and Prime Factors' with 50% accuracy over 8 attempts.",
    "keywords": "Prime Numbers and Prime Factors",
    "stats": {
      "correct": 4,
      "total": 8
    }
  },
  "memory": [
    {
      "description": "The student struggled to apply Prime Numbers and Prime Factors.",
      "timestamp": 1572136680000,
      "response": 0
    },
    {
      "description": "The student answered a Prime Numbers and Prime Factors question incorrectly.",
      "timestamp": 1572147300000,
      "response": 0
    },
    {
      "description": "The student correctly applied Prime Numbers and Prime Factors knowledge.",
      "timestamp": 1572147360000,
      "response": 1
    },
    {
      "description": "The student got a Prime Numbers and Prime Factors problem wrong.",
      "timestamp": 1572147360000,
      "response": 0
    },
    {
      "description": "The student nailed the Prime Numbers and Prime Factors concept.",
      "timestamp": 1573277160000,
      "response": 1
    },
    {
      "description": "The student demonstrated proficiency in Prime Numbers and Prime Factors.",
      "timestamp": 1574136780000,
      "response": 1
    },
    {
      "description": "The student faced difficulty understanding Prime Numbers and Prime Factors.",
      "timestamp": 1574136840000,
      "response": 0
    },
    {
      "description": "The student solved a Prime Numbers and Prime Factors problem with ease.",
      "timestamp": 1574136840000,
      "response": 1
    }
  ],
  "delta_t_days": 3164.625,
  "delta_t_minutes": 4557060.0,
  "tau_minutes": 300.0,
  "last_response": 0,
  "num_attempts": 9,
  "methods": {
    "history": {
      "s_tc": 0.5,
      "fs": 0.4999670862078045,
      "level": "high"
    },
    "lpkt": {
      "s_tc": 0.6003862619400024,
      "fs": 0.3995874324529316,
      "level": "high"
    },
    "dkt": {
      "s_tc": 0.6167054772377014,
      "fs": 0.38326929140975485,
      "level": "high"
    },
    "akt": {
      "s_tc": 0.3854566812515259,
      "fs": 0.6145028648462972,
      "level": "high"
    },
    "simplekt": {
      "s_tc": 0.0,
      "fs": 0.999934172415609,
      "level": "high"
    }
  }
}