{
  "student_id": "724",
  "concept_id": 18,
  "concept_text": "Enter larger initial in diagram -- given",
  "persona": {
    "description": "Student shows excellent mastery of 'Enter larger initial in diagram -- given' with 100% accuracy over 11 attempts.",
    "keywords": "Enter larger initial in diagram -- given",
    "stats": {
      "correct": 11,
      "total": 11
    }
  },
  "memory": [
    {
      "description": "The student mastered the Enter larger initial in diagram -- given task.",
      "timestamp": 1161889477000,
      "response": 1
    },
    {
      "description": "The student skillfully worked through Enter larger initial in diagram -- given.",
      "timestamp": 1161889807000,
      "response": 1
    },
    {
      "description": "The student answered a Enter larger initial in diagram -- given question accurately.",
      "timestamp": 1161890309000,
      "response": 1
    },
    {
      "description": "The student demonstrated proficiency in Enter larger initial in diagram -- given.",
      "timestamp": 1161890405000,
      "response": 1
    },
    {
      "description": "The student showed mastery of Enter larger initial in diagram -- given in this attempt.",
      "timestamp": 1161890505000,
      "response": 1
    },
    {
      "description": "The student successfully solved a Enter larger initial in diagram -- given problem.",
      "timestamp": 1161890595000,
      "response": 1
    },
    {
      "description": "The student mastered the Enter larger initial in diagram -- given task.",
      "timestamp": 1161890685000,
      "response": 1
    },
    {
      "description": "The student answered a Enter larger initial in diagram -- given question accurately.",
      "timestamp": 1177529890000,
      "response": 1
    },
    {
      "description": "The student mastered the Enter larger initial in diagram -- given task.",
      "timestamp": 1177530431000,
      "response": 1
    },
    {
      "description": "The student correctly answered a question on Enter larger initial in diagram -- given.",
      "timestamp": 1177530541000,
      "response": 1
    },
    {
      "description": "The student answered a Enter larger initial in diagram -- given question accurately.",
      "timestamp": 1177613699000,
      "response": 1
    }
  ],
  "delta_t_days": 0.0024074074074074076,
  "delta_t_minutes": 3.466666666666667,
  "tau_minutes": 2.5,
  "last_response": 1,
  "num_attempts": 12,
  "methods": {
    "history": {
      "s_tc": 1.0,
      "fs": 0.0,
      "level": "low"
    },
    "lpkt": {
      "s_tc": 0.8721725344657898,
      "fs": 0.07426847159529532,
      "level": "medium"
    },
    "dkt": {
      "s_tc": 0.8892660140991211,
      "fs": 0.06433706443403021,
      "level": "medium"
    },
    "akt": {
      "s_tc": 0.9540555477142334,
      "fs": 0.026693983450948196,
      "level": "medium"
    },
    "simplekt": {
      "s_tc": 1.0,
      "fs": 0.0,
      "level": "medium"
    }
  }
}