{
  "student_id": "767",
  "concept_id": 20,
  "concept_text": "Calculate product of two numbers",
  "persona": {
    "description": "Student shows needs improvement of 'Calculate product of two numbers' with 54% accuracy over 13 attempts.",
    "keywords": "Calculate product of two numbers",
    "stats": {
      "correct": 7,
      "total": 13
    }
  },
  "memory": [
    {
      "description": "The student confidently handled Calculate product of two numbers.",
      "timestamp": 1161283221000,
      "response": 1
    },
    {
      "description": "The student stumbled on Calculate product of two numbers.",
      "timestamp": 1161283375000,
      "response": 0
    },
    {
      "description": "The student made a mistake on Calculate product of two numbers.",
      "timestamp": 1161367555000,
      "response": 0
    },
    {
      "description": "The student had difficulty with a Calculate product of two numbers question.",
      "timestamp": 1161367695000,
      "response": 0
    },
    {
      "description": "The student missed a Calculate product of two numbers question.",
      "timestamp": 1161367766000,
      "response": 0
    },
    {
      "description": "The student encountered challenges with Calculate product of two numbers.",
      "timestamp": 1161367873000,
      "response": 0
    },
    {
      "description": "The student demonstrated understanding of Calculate product of two numbers by answering correctly.",
      "timestamp": 1161368095000,
      "response": 1
    },
    {
      "description": "The student tackled a Calculate product of two numbers question and got it right.",
      "timestamp": 1161368227000,
      "response": 1
    },
    {
      "description": "The student correctly answered a question on Calculate product of two numbers.",
      "timestamp": 1161368424000,
      "response": 1
    },
    {
      "description": "The student nailed the Calculate product of two numbers concept.",
      "timestamp": 1161368622000,
      "response": 1
    },
    {
      "description": "The student answered a Calculate product of two numbers question accurately.",
      "timestamp": 1161368692000,
      "response": 1
    },
    {
      "description": "The student aced a problem involving Calculate product of two numbers.",
      "timestamp": 1161368802000,
      "response": 1
    },
    {
      "description": "The student stumbled on Calculate product of two numbers.",
      "timestamp": 1161885793000,
      "response": 0
    }
  ],
  "delta_t_days": 0.002025462962962963,
  "delta_t_minutes": 2.9166666666666665,
  "tau_minutes": 2.5,
  "last_response": 1,
  "num_attempts": 14,
  "methods": {
    "history": {
      "s_tc": 0.5384615384615384,
      "fs": 0.24852071005917165,
      "level": "high"
    },
    "dkt": {
      "s_tc": 0.3098120391368866,
      "fs": 0.3716396712339842,
      "level": "high"
    },
    "akt": {
      "s_tc": 0.24571871757507324,
      "fs": 0.4061514597672683,
      "level": "high"
    },
    "simplekt": {
      "s_tc": 0.0,
      "fs": 0.5384615384615385,
      "level": "high"
    }
  }
}