{
  "student_id": "916",
  "concept_id": 12,
  "concept_text": "pythagorean-theorem",
  "persona": {
    "description": "Student shows needs improvement of 'pythagorean-theorem' with 20% accuracy over 10 attempts.",
    "keywords": "pythagorean-theorem",
    "stats": {
      "correct": 2,
      "total": 10
    }
  },
  "memory": [
    {
      "description": "The student fumbled a pythagorean-theorem problem.",
      "timestamp": 1131381105000,
      "response": 0
    },
    {
      "description": "The student fumbled a pythagorean-theorem problem.",
      "timestamp": 1131381145000,
      "response": 0
    },
    {
      "description": "The student aced a problem involving pythagorean-theorem.",
      "timestamp": 1131381152000,
      "response": 1
    },
    {
      "description": "The student encountered challenges with pythagorean-theorem.",
      "timestamp": 1142871850000,
      "response": 0
    },
    {
      "description": "The student skillfully worked through pythagorean-theorem.",
      "timestamp": 1142871892000,
      "response": 1
    },
    {
      "description": "The student encountered challenges with pythagorean-theorem.",
      "timestamp": 1146068344000,
      "response": 0
    },
    {
      "description": "The student encountered challenges with pythagorean-theorem.",
      "timestamp": 1146068347000,
      "response": 0
    },
    {
      "description": "The student encountered challenges with pythagorean-theorem.",
      "timestamp": 1146068348000,
      "response": 0
    },
    {
      "description": "The student encountered challenges with pythagorean-theorem.",
      "timestamp": 1146068349000,
      "response": 0
    },
    {
      "description": "The student encountered challenges with pythagorean-theorem.",
      "timestamp": 1146068349000,
      "response": 0
    }
  ],
  "delta_t_days": 0.0006944444444444445,
  "delta_t_minutes": 1.0,
  "tau_minutes": 23.0,
  "last_response": 1,
  "num_attempts": 11,
  "methods": {
    "history": {
      "s_tc": 0.2,
      "fs": 0.03333333333333333,
      "level": "low"
    },
    "lpkt": {
      "s_tc": 0.40493881702423096,
      "fs": 0.024794215957323708,
      "level": "low"
    },
    "dkt": {
      "s_tc": 0.6148073077201843,
      "fs": 0.016049695511658985,
      "level": "low"
    },
    "akt": {
      "s_tc": 0.5496034026145935,
      "fs": 0.0187665248910586,
      "level": "low"
    },
    "simplekt": {
      "s_tc": 0.0,
      "fs": 0.041666666666666664,
      "level": "low"
    }
  }
}