[
  {
    "concept_id": 21,
    "concept_text": "noskill",
    "description": "Student shows needs improvement of 'noskill' with 35% accuracy over 178 attempts.",
    "keywords": "noskill",
    "stats": {
      "correct": 62,
      "total": 178
    }
  },
  {
    "concept_id": 34,
    "concept_text": "equation-solving",
    "description": "Student shows needs improvement of 'equation-solving' with 20% accuracy over 5 attempts.",
    "keywords": "equation-solving",
    "stats": {
      "correct": 1,
      "total": 5
    }
  },
  {
    "concept_id": 14,
    "concept_text": "pattern-finding",
    "description": "Student shows good understanding of 'pattern-finding' with 67% accuracy over 9 attempts.",
    "keywords": "pattern-finding",
    "stats": {
      "correct": 6,
      "total": 9
    }
  },
  {
    "concept_id": 75,
    "concept_text": "circle-graph",
    "description": "Student shows needs improvement of 'circle-graph' with 20% accuracy over 5 attempts.",
    "keywords": "circle-graph",
    "stats": {
      "correct": 1,
      "total": 5
    }
  },
  {
    "concept_id": 54,
    "concept_text": "finding-percents",
    "description": "Student shows needs improvement of 'finding-percents' with 0% accuracy over 6 attempts.",
    "keywords": "finding-percents",
    "stats": {
      "correct": 0,
      "total": 6
    }
  },
  {
    "concept_id": 58,
    "concept_text": "probability",
    "description": "Student shows excellent mastery of 'probability' with 100% accuracy over 1 attempts.",
    "keywords": "probability",
    "stats": {
      "correct": 1,
      "total": 1
    }
  },
  {
    "concept_id": 56,
    "concept_text": "integers",
    "description": "Student shows needs improvement of 'integers' with 50% accuracy over 2 attempts.",
    "keywords": "integers",
    "stats": {
      "correct": 1,
      "total": 2
    }
  },
  {
    "concept_id": 43,
    "concept_text": "ordering-numbers",
    "description": "Student shows good understanding of 'ordering-numbers' with 67% accuracy over 3 attempts.",
    "keywords": "ordering-numbers",
    "stats": {
      "correct": 2,
      "total": 3
    }
  },
  {
    "concept_id": 70,
    "concept_text": "equation-concept",
    "description": "Student shows needs improvement of 'equation-concept' with 50% accuracy over 6 attempts.",
    "keywords": "equation-concept",
    "stats": {
      "correct": 3,
      "total": 6
    }
  },
  {
    "concept_id": 69,
    "concept_text": "unit-conversion",
    "description": "Student shows needs improvement of 'unit-conversion' with 25% accuracy over 68 attempts.",
    "keywords": "unit-conversion",
    "stats": {
      "correct": 17,
      "total": 68
    }
  },
  {
    "concept_id": 8,
    "concept_text": "isosceles-triangle",
    "description": "Student shows needs improvement of 'isosceles-triangle' with 25% accuracy over 4 attempts.",
    "keywords": "isosceles-triangle",
    "stats": {
      "correct": 1,
      "total": 4
    }
  },
  {
    "concept_id": 31,
    "concept_text": "transversals",
    "description": "Student shows needs improvement of 'transversals' with 0% accuracy over 3 attempts.",
    "keywords": "transversals",
    "stats": {
      "correct": 0,
      "total": 3
    }
  },
  {
    "concept_id": 12,
    "concept_text": "pythagorean-theorem",
    "description": "Student shows needs improvement of 'pythagorean-theorem' with 21% accuracy over 19 attempts.",
    "keywords": "pythagorean-theorem",
    "stats": {
      "correct": 4,
      "total": 19
    }
  },
  {
    "concept_id": 3,
    "concept_text": "transformations-rotations",
    "description": "Student shows needs improvement of 'transformations-rotations' with 0% accuracy over 3 attempts.",
    "keywords": "transformations-rotations",
    "stats": {
      "correct": 0,
      "total": 3
    }
  },
  {
    "concept_id": 4,
    "concept_text": "reading-graph",
    "description": "Student shows needs improvement of 'reading-graph' with 27% accuracy over 11 attempts.",
    "keywords": "reading-graph",
    "stats": {
      "correct": 3,
      "total": 11
    }
  },
  {
    "concept_id": 0,
    "concept_text": "properties-of-geometric-figures",
    "description": "Student shows needs improvement of 'properties-of-geometric-figures' with 12% accuracy over 16 attempts.",
    "keywords": "properties-of-geometric-figures",
    "stats": {
      "correct": 2,
      "total": 16
    }
  },
  {
    "concept_id": 2,
    "concept_text": "point-plotting",
    "description": "Student shows needs improvement of 'point-plotting' with 50% accuracy over 4 attempts.",
    "keywords": "point-plotting",
    "stats": {
      "correct": 2,
      "total": 4
    }
  },
  {
    "concept_id": 32,
    "concept_text": "triangle-inequality",
    "description": "Student shows needs improvement of 'triangle-inequality' with 0% accuracy over 4 attempts.",
    "keywords": "triangle-inequality",
    "stats": {
      "correct": 0,
      "total": 4
    }
  },
  {
    "concept_id": 65,
    "concept_text": "linear-area-volume-conversion",
    "description": "Student shows needs improvement of 'linear-area-volume-conversion' with 18% accuracy over 11 attempts.",
    "keywords": "linear-area-volume-conversion",
    "stats": {
      "correct": 2,
      "total": 11
    }
  },
  {
    "concept_id": 78,
    "concept_text": "fraction-decimals-percents",
    "description": "Student shows needs improvement of 'fraction-decimals-percents' with 43% accuracy over 7 attempts.",
    "keywords": "fraction-decimals-percents",
    "stats": {
      "correct": 3,
      "total": 7
    }
  },
  {
    "concept_id": 13,
    "concept_text": "interpreting-linear-equations",
    "description": "Student shows needs improvement of 'interpreting-linear-equations' with 20% accuracy over 35 attempts.",
    "keywords": "interpreting-linear-equations",
    "stats": {
      "correct": 7,
      "total": 35
    }
  },
  {
    "concept_id": 45,
    "concept_text": "evaluating-functions",
    "description": "Student shows needs improvement of 'evaluating-functions' with 0% accuracy over 4 attempts.",
    "keywords": "evaluating-functions",
    "stats": {
      "correct": 0,
      "total": 4
    }
  },
  {
    "concept_id": 33,
    "concept_text": "multiplication",
    "description": "Student shows needs improvement of 'multiplication' with 0% accuracy over 4 attempts.",
    "keywords": "multiplication",
    "stats": {
      "correct": 0,
      "total": 4
    }
  },
  {
    "concept_id": 5,
    "concept_text": "area",
    "description": "Student shows needs improvement of 'area' with 13% accuracy over 15 attempts.",
    "keywords": "area",
    "stats": {
      "correct": 2,
      "total": 15
    }
  },
  {
    "concept_id": 35,
    "concept_text": "discount",
    "description": "Student shows needs improvement of 'discount' with 33% accuracy over 3 attempts.",
    "keywords": "discount",
    "stats": {
      "correct": 1,
      "total": 3
    }
  },
  {
    "concept_id": 25,
    "concept_text": "percent-of",
    "description": "Student shows needs improvement of 'percent-of' with 0% accuracy over 9 attempts.",
    "keywords": "percent-of",
    "stats": {
      "correct": 0,
      "total": 9
    }
  },
  {
    "concept_id": 46,
    "concept_text": "substitution",
    "description": "Student shows needs improvement of 'substitution' with 0% accuracy over 3 attempts.",
    "keywords": "substitution",
    "stats": {
      "correct": 0,
      "total": 3
    }
  },
  {
    "concept_id": 26,
    "concept_text": "venn-diagram",
    "description": "Student shows needs improvement of 'venn-diagram' with 17% accuracy over 6 attempts.",
    "keywords": "venn-diagram",
    "stats": {
      "correct": 1,
      "total": 6
    }
  },
  {
    "concept_id": 6,
    "concept_text": "perimeter",
    "description": "Student shows needs improvement of 'perimeter' with 50% accuracy over 2 attempts.",
    "keywords": "perimeter",
    "stats": {
      "correct": 1,
      "total": 2
    }
  }
]