{
  "0": {
    "concept_id": 0,
    "concept_text": "Identify larger quantity -- multiplication",
    "question_id": 32,
    "response": 1,
    "timestamp": 1160154187000
  },
  "2": {
    "concept_id": 2,
    "concept_text": "Draw smaller bar -- multiplication",
    "question_id": 33,
    "response": 0,
    "timestamp": 1160154190000
  },
  "1": {
    "concept_id": 1,
    "concept_text": "Draw larger bar -- multiplication",
    "question_id": 34,
    "response": 1,
    "timestamp": 1160154210000
  },
  "3": {
    "concept_id": 3,
    "concept_text": "Enter smaller initial in diagram -- given",
    "question_id": 35,
    "response": 1,
    "timestamp": 1160154214000
  },
  "4": {
    "concept_id": 4,
    "concept_text": "Enter larger inital in diagram -- calculated",
    "question_id": 36,
    "response": 1,
    "timestamp": 1160154230000
  },
  "5": {
    "concept_id": 5,
    "concept_text": "Enter total in diagram - calculated - multiplication",
    "question_id": 37,
    "response": 1,
    "timestamp": 1160154233000
  },
  "6": {
    "concept_id": 6,
    "concept_text": "Enter quantity from diagram by reading",
    "question_id": 43947,
    "response": 1,
    "timestamp": 1160155219000
  },
  "7": {
    "concept_id": 7,
    "concept_text": "Identify larger quantity -- addition",
    "question_id": 31133,
    "response": 0,
    "timestamp": 1160154565000
  },
  "8": {
    "concept_id": 8,
    "concept_text": "Draw smaller bar -- addition/subtraction",
    "question_id": 43949,
    "response": 1,
    "timestamp": 1160155234000
  },
  "9": {
    "concept_id": 9,
    "concept_text": "Draw larger bar -- addition/subtraction",
    "question_id": 43950,
    "response": 0,
    "timestamp": 1160155236000
  },
  "10": {
    "concept_id": 10,
    "concept_text": "Copy initial in diagram",
    "question_id": 31137,
    "response": 1,
    "timestamp": 1160154581000
  },
  "12": {
    "concept_id": 12,
    "concept_text": "Enter initial in diagram -- given",
    "question_id": 31136,
    "response": 1,
    "timestamp": 1160154579000
  },
  "11": {
    "concept_id": 11,
    "concept_text": "Enter added quantity in diagram",
    "question_id": 31138,
    "response": 1,
    "timestamp": 1160154582000
  },
  "13": {
    "concept_id": 13,
    "concept_text": "Enter total in diagram - calculated - addition",
    "question_id": 31139,
    "response": 1,
    "timestamp": 1160154597000
  },
  "14": {
    "concept_id": 14,
    "concept_text": "Enter quantity from diagram by calculating",
    "question_id": 31141,
    "response": 1,
    "timestamp": 1160154605000
  },
  "15": {
    "concept_id": 15,
    "concept_text": "Identify larger quantity -- subtraction",
    "question_id": 43948,
    "response": 0,
    "timestamp": 1160155230000
  },
  "16": {
    "concept_id": 16,
    "concept_text": "Enter smaller inital in diagram -- calculated",
    "question_id": 43942,
    "response": 1,
    "timestamp": 1160155204000
  },
  "17": {
    "concept_id": 17,
    "concept_text": "Enter subtracted quantity in diagram",
    "question_id": 43944,
    "response": 1,
    "timestamp": 1160155211000
  },
  "18": {
    "concept_id": 18,
    "concept_text": "Enter larger initial in diagram -- given",
    "question_id": 43951,
    "response": 1,
    "timestamp": 1160155244000
  },
  "19": {
    "concept_id": 19,
    "concept_text": "Enter total in diagram - calculated - subtraction",
    "question_id": 43945,
    "response": 1,
    "timestamp": 1160155214000
  },
  "20": {
    "concept_id": 20,
    "concept_text": "Calculate product of two numbers",
    "question_id": 1350,
    "response": 1,
    "timestamp": 1160156874000
  },
  "21": {
    "concept_id": 21,
    "concept_text": "List consecutive multiples of a number",
    "question_id": 1368,
    "response": 1,
    "timestamp": 1160156903000
  },
  "22": {
    "concept_id": 22,
    "concept_text": "Identify number as common multiple",
    "question_id": 1379,
    "response": 1,
    "timestamp": 1160156921000
  },
  "23": {
    "concept_id": 23,
    "concept_text": "Identify LCM - is product",
    "question_id": 1859,
    "response": 1,
    "timestamp": 1160156183000
  },
  "24": {
    "concept_id": 24,
    "concept_text": "Identify LCM - one number multiple of other",
    "question_id": 2032,
    "response": 0,
    "timestamp": 1160156843000
  },
  "25": {
    "concept_id": 25,
    "concept_text": "Identify LCM",
    "question_id": 5527,
    "response": 1,
    "timestamp": 1160156781000
  },
  "28": {
    "concept_id": 28,
    "concept_text": "List factor of large number",
    "question_id": 43978,
    "response": 1,
    "timestamp": 1160760996000
  },
  "27": {
    "concept_id": 27,
    "concept_text": "Identify number as common factor",
    "question_id": 43979,
    "response": 1,
    "timestamp": 1160760999000
  },
  "29": {
    "concept_id": 29,
    "concept_text": "Identify GCF - one number multiple of other",
    "question_id": 2841,
    "response": 1,
    "timestamp": 1160760211000
  },
  "26": {
    "concept_id": 26,
    "concept_text": "Identify GCF",
    "question_id": 43952,
    "response": 0,
    "timestamp": 1160760289000
  },
  "30": {
    "concept_id": 30,
    "concept_text": "Identify number of items in each group from GCF",
    "question_id": 43970,
    "response": 0,
    "timestamp": 1160760464000
  },
  "31": {
    "concept_id": 31,
    "concept_text": "Identify number of equal divisions (vertical bar)",
    "question_id": 28835,
    "response": 1,
    "timestamp": 1161970565000
  },
  "32": {
    "concept_id": 32,
    "concept_text": "Identify fraction associated with each piece of a vertical bar",
    "question_id": 28836,
    "response": 1,
    "timestamp": 1161970567000
  },
  "33": {
    "concept_id": 33,
    "concept_text": "Count number of shaded parts in vertical bar (discontiguous)",
    "question_id": 5821,
    "response": 1,
    "timestamp": 1161970290000
  },
  "34": {
    "concept_id": 34,
    "concept_text": "Identify Fraction using fraction shape",
    "question_id": 5822,
    "response": 1,
    "timestamp": 1161970292000
  },
  "35": {
    "concept_id": 35,
    "concept_text": "Identify number of equal divisions (square)",
    "question_id": 37581,
    "response": 1,
    "timestamp": 1161970671000
  },
  "36": {
    "concept_id": 36,
    "concept_text": "Identify fraction associated with each piece of a square",
    "question_id": 37582,
    "response": 1,
    "timestamp": 1161970674000
  },
  "37": {
    "concept_id": 37,
    "concept_text": "Count number of shaded parts in square (contiguous)",
    "question_id": 30917,
    "response": 1,
    "timestamp": 1161970180000
  },
  "38": {
    "concept_id": 38,
    "concept_text": "Identify number of equal divisions (circle)",
    "question_id": 28845,
    "response": 1,
    "timestamp": 1161970604000
  },
  "39": {
    "concept_id": 39,
    "concept_text": "Identify fraction associated with each piece of a circle",
    "question_id": 28846,
    "response": 1,
    "timestamp": 1161970607000
  },
  "40": {
    "concept_id": 40,
    "concept_text": "Count number of shaded parts in circle (contiguous)",
    "question_id": 5805,
    "response": 1,
    "timestamp": 1161970051000
  },
  "47": {
    "concept_id": 47,
    "concept_text": "Count number of shaded parts in square (discontiguous)",
    "question_id": 6290,
    "response": 1,
    "timestamp": 1161970066000
  },
  "42": {
    "concept_id": 42,
    "concept_text": "Identify number of equal divisions (horizontal bar)",
    "question_id": 30944,
    "response": 1,
    "timestamp": 1161970588000
  },
  "43": {
    "concept_id": 43,
    "concept_text": "Identify fraction associated with each piece of a horizontal bar",
    "question_id": 30945,
    "response": 1,
    "timestamp": 1161970594000
  },
  "45": {
    "concept_id": 45,
    "concept_text": "Count number of shaded parts in horizontal bar (contiguous)",
    "question_id": 7901,
    "response": 1,
    "timestamp": 1161970235000
  },
  "46": {
    "concept_id": 46,
    "concept_text": "Count number of shaded parts in circle (discontiguous)",
    "question_id": 6246,
    "response": 1,
    "timestamp": 1161970161000
  },
  "41": {
    "concept_id": 41,
    "concept_text": "Count number of shaded parts in vertical bar (contiguous)",
    "question_id": 31935,
    "response": 1,
    "timestamp": 1161970033000
  },
  "44": {
    "concept_id": 44,
    "concept_text": "Count number of shaded parts in horizontal bar (discontiguous)",
    "question_id": 2866,
    "response": 1,
    "timestamp": 1161970255000
  },
  "48": {
    "concept_id": 48,
    "concept_text": "Identify number of desired items",
    "question_id": 3793,
    "response": 1,
    "timestamp": 1161970881000
  },
  "49": {
    "concept_id": 49,
    "concept_text": "Identify number of total items",
    "question_id": 3791,
    "response": 1,
    "timestamp": 1161970865000
  },
  "50": {
    "concept_id": 50,
    "concept_text": "Identify fraction of desired items",
    "question_id": 3794,
    "response": 1,
    "timestamp": 1161970885000
  },
  "51": {
    "concept_id": 51,
    "concept_text": "Identify number of equal groups from fraction",
    "question_id": 4324,
    "response": 1,
    "timestamp": 1169231676000
  },
  "52": {
    "concept_id": 52,
    "concept_text": "Identify number of desired groups--construct",
    "question_id": 3796,
    "response": 1,
    "timestamp": 1161970901000
  },
  "53": {
    "concept_id": 53,
    "concept_text": "Identify number of items",
    "question_id": 8729,
    "response": 1,
    "timestamp": 1165602392000
  },
  "55": {
    "concept_id": 55,
    "concept_text": "Identify proper fraction from option 1",
    "question_id": 8728,
    "response": 0,
    "timestamp": 1165602354000
  },
  "54": {
    "concept_id": 54,
    "concept_text": "Identify number of recipients",
    "question_id": 8730,
    "response": 1,
    "timestamp": 1165602394000
  },
  "56": {
    "concept_id": 56,
    "concept_text": "Identify proper fraction from option 2",
    "question_id": 8731,
    "response": 0,
    "timestamp": 1165602396000
  },
  "57": {
    "concept_id": 57,
    "concept_text": "Compare Options - operation",
    "question_id": 8732,
    "response": 1,
    "timestamp": 1165602525000
  },
  "58": {
    "concept_id": 58,
    "concept_text": "Compare Options - simplified",
    "question_id": 14272,
    "response": 0,
    "timestamp": 1165601824000
  },
  "59": {
    "concept_id": 59,
    "concept_text": "Identify improper fraction from option 1",
    "question_id": 14317,
    "response": 1,
    "timestamp": 1165601619000
  },
  "60": {
    "concept_id": 60,
    "concept_text": "Identify improper fraction from option 2",
    "question_id": 14320,
    "response": 1,
    "timestamp": 1165601637000
  },
  "61": {
    "concept_id": 61,
    "concept_text": "Identify number of desired groups",
    "question_id": 4325,
    "response": 1,
    "timestamp": 1169231681000
  },
  "62": {
    "concept_id": 62,
    "concept_text": "Identify number of items in each group",
    "question_id": 4326,
    "response": 1,
    "timestamp": 1169231689000
  },
  "63": {
    "concept_id": 63,
    "concept_text": "Calculate Part",
    "question_id": 8744,
    "response": 0,
    "timestamp": 1169230518000
  },
  "64": {
    "concept_id": 64,
    "concept_text": "Enter group numerator",
    "question_id": 4328,
    "response": 1,
    "timestamp": 1169231698000
  },
  "65": {
    "concept_id": 65,
    "concept_text": "Enter group denominator",
    "question_id": 4329,
    "response": 1,
    "timestamp": 1169231699000
  },
  "66": {
    "concept_id": 66,
    "concept_text": "Enter items numerator",
    "question_id": 4330,
    "response": 1,
    "timestamp": 1169231703000
  },
  "67": {
    "concept_id": 67,
    "concept_text": "Enter items denominator",
    "question_id": 4331,
    "response": 1,
    "timestamp": 1169231705000
  },
  "68": {
    "concept_id": 68,
    "concept_text": "Calculate Total",
    "question_id": 4327,
    "response": 1,
    "timestamp": 1169231695000
  },
  "69": {
    "concept_id": 69,
    "concept_text": "Identify multiplier in written question -- rectangle",
    "question_id": 30262,
    "response": 1,
    "timestamp": 1170441470000
  },
  "70": {
    "concept_id": 70,
    "concept_text": "Identify multiplier in equivalence statement",
    "question_id": 4454,
    "response": 1,
    "timestamp": 1171043672000
  },
  "72": {
    "concept_id": 72,
    "concept_text": "Label equivalent fraction in visual",
    "question_id": 33229,
    "response": 1,
    "timestamp": 1172253845000
  },
  "71": {
    "concept_id": 71,
    "concept_text": "Label equivalent fraction in equivalence statement",
    "question_id": 33240,
    "response": 1,
    "timestamp": 1172254195000
  },
  "73": {
    "concept_id": 73,
    "concept_text": "Identify number of equal divisions on number line from desired denominator",
    "question_id": 4451,
    "response": 1,
    "timestamp": 1171043654000
  },
  "74": {
    "concept_id": 74,
    "concept_text": "Label equivalent fraction on number line",
    "question_id": 33241,
    "response": 1,
    "timestamp": 1172254197000
  },
  "75": {
    "concept_id": 75,
    "concept_text": "Identify multiplier in written question -- number line",
    "question_id": 4453,
    "response": 1,
    "timestamp": 1171043670000
  },
  "76": {
    "concept_id": 76,
    "concept_text": "Identify GCF in written question",
    "question_id": 33238,
    "response": 1,
    "timestamp": 1172254181000
  },
  "77": {
    "concept_id": 77,
    "concept_text": "Identify GCF in equivalence statement",
    "question_id": 33239,
    "response": 1,
    "timestamp": 1172254187000
  },
  "78": {
    "concept_id": 78,
    "concept_text": "Identify common denominator",
    "question_id": 44108,
    "response": 0,
    "timestamp": 1175269784000
  },
  "79": {
    "concept_id": 79,
    "concept_text": "Rewrite fraction with common denominator",
    "question_id": 44111,
    "response": 1,
    "timestamp": 1175269845000
  },
  "80": {
    "concept_id": 80,
    "concept_text": "Compare fractions with like denominators",
    "question_id": 44051,
    "response": 1,
    "timestamp": 1173463667000
  },
  "81": {
    "concept_id": 81,
    "concept_text": "Compare fractions with unlike denominators",
    "question_id": 44052,
    "response": 0,
    "timestamp": 1173463668000
  },
  "82": {
    "concept_id": 82,
    "concept_text": "Compare fractions from contextual problem",
    "question_id": 44053,
    "response": 1,
    "timestamp": 1173463671000
  },
  "83": {
    "concept_id": 83,
    "concept_text": "Calculate sum -- non contextual",
    "question_id": 4717,
    "response": 1,
    "timestamp": 1175269641000
  },
  "84": {
    "concept_id": 84,
    "concept_text": "Identify that a fraction cannot be simplified",
    "question_id": 4724,
    "response": 1,
    "timestamp": 1175269668000
  },
  "85": {
    "concept_id": 85,
    "concept_text": "Calculate difference -- contextual",
    "question_id": 29241,
    "response": 1,
    "timestamp": 1175269728000
  },
  "86": {
    "concept_id": 86,
    "concept_text": "Calculate sum -- contextual",
    "question_id": 9027,
    "response": 1,
    "timestamp": 1175269701000
  },
  "87": {
    "concept_id": 87,
    "concept_text": "Identify that a fraction can be simplified",
    "question_id": 29282,
    "response": 1,
    "timestamp": 1175269772000
  },
  "88": {
    "concept_id": 88,
    "concept_text": "Calculate difference -- non contextual",
    "question_id": 29283,
    "response": 1,
    "timestamp": 1175269777000
  },
  "89": {
    "concept_id": 89,
    "concept_text": "Represent first fraction on number line",
    "question_id": 44110,
    "response": 0,
    "timestamp": 1175269837000
  },
  "90": {
    "concept_id": 90,
    "concept_text": "Represent second fraction on number line as sum",
    "question_id": 4728,
    "response": 1,
    "timestamp": 1175269689000
  },
  "91": {
    "concept_id": 91,
    "concept_text": "Represent second fraction on number line as difference",
    "question_id": 44112,
    "response": 1,
    "timestamp": 1175269850000
  },
  "92": {
    "concept_id": 92,
    "concept_text": "Identify whole number lower bound",
    "question_id": 37742,
    "response": 1,
    "timestamp": 1175534281000
  },
  "93": {
    "concept_id": 93,
    "concept_text": "Identify whole number upper bound",
    "question_id": 37743,
    "response": 0,
    "timestamp": 1175534285000
  },
  "94": {
    "concept_id": 94,
    "concept_text": "Identify number of equal divisions in visual from fraction",
    "question_id": 6976,
    "response": 1,
    "timestamp": 1175534356000
  },
  "95": {
    "concept_id": 95,
    "concept_text": "Identify whole number of mixed number symbolically",
    "question_id": 37745,
    "response": 1,
    "timestamp": 1175534336000
  },
  "96": {
    "concept_id": 96,
    "concept_text": "Identify fractional part of mixed number symbolically",
    "question_id": 37746,
    "response": 1,
    "timestamp": 1175534339000
  },
  "97": {
    "concept_id": 97,
    "concept_text": "Convert whole number to improper fraction",
    "question_id": 37747,
    "response": 1,
    "timestamp": 1175534342000
  },
  "98": {
    "concept_id": 98,
    "concept_text": "Isolate numerator of fractional part of mixed number symbolically",
    "question_id": 37748,
    "response": 1,
    "timestamp": 1175534344000
  },
  "99": {
    "concept_id": 99,
    "concept_text": "Write mixed number as improper fraction",
    "question_id": 37749,
    "response": 1,
    "timestamp": 1175534347000
  },
  "104": {
    "concept_id": 104,
    "concept_text": "Identify equal parts for multiplicand",
    "question_id": 44213,
    "response": 1,
    "timestamp": 1178904095000
  },
  "105": {
    "concept_id": 105,
    "concept_text": "Identify equal parts for multiplier",
    "question_id": 44214,
    "response": 1,
    "timestamp": 1178904098000
  },
  "106": {
    "concept_id": 106,
    "concept_text": "Represent multiplier visually",
    "question_id": 44216,
    "response": 1,
    "timestamp": 1178904103000
  },
  "107": {
    "concept_id": 107,
    "concept_text": "Represent multiplicand visually",
    "question_id": 44215,
    "response": 1,
    "timestamp": 1178904101000
  },
  "108": {
    "concept_id": 108,
    "concept_text": "Identify length of overlap",
    "question_id": 44217,
    "response": 1,
    "timestamp": 1178904106000
  },
  "109": {
    "concept_id": 109,
    "concept_text": "Identify width of overlap",
    "question_id": 44218,
    "response": 1,
    "timestamp": 1178904108000
  },
  "110": {
    "concept_id": 110,
    "concept_text": "Calculate area of overlap",
    "question_id": 44219,
    "response": 1,
    "timestamp": 1178904112000
  },
  "111": {
    "concept_id": 111,
    "concept_text": "Calculate product -- multiply statement",
    "question_id": 44220,
    "response": 1,
    "timestamp": 1178904115000
  },
  "112": {
    "concept_id": 112,
    "concept_text": "Identify that a fraction can/cannot be simplified",
    "question_id": 44221,
    "response": 1,
    "timestamp": 1178904117000
  },
  "113": {
    "concept_id": 113,
    "concept_text": "Calculate product -- of statement",
    "question_id": 44201,
    "response": 1,
    "timestamp": 1178903951000
  },
  "114": {
    "concept_id": 114,
    "concept_text": "Simplify fraction",
    "question_id": 44212,
    "response": 1,
    "timestamp": 1178904061000
  },
  "125": {
    "concept_id": 125,
    "concept_text": "[SkillRule: Invert divisor and multiply; Invert and Multiply]",
    "question_id": 37895,
    "response": 0,
    "timestamp": 1178904949000
  },
  "126": {
    "concept_id": 126,
    "concept_text": "[SkillRule: Perform invert divisor and multiply; [Typein Skill: Invert divisor and multiply]]",
    "question_id": 37896,
    "response": 0,
    "timestamp": 1179506939000
  },
  "127": {
    "concept_id": 127,
    "concept_text": "[SkillRule: Select multiply through; Multiply through]",
    "question_id": 44223,
    "response": 1,
    "timestamp": 1179506975000
  },
  "121": {
    "concept_id": 121,
    "concept_text": "[SkillRule: Write improper fraction as mixed number; Rewrite term as mixed number]",
    "question_id": 9390,
    "response": 0,
    "timestamp": 1178904677000
  },
  "128": {
    "concept_id": 128,
    "concept_text": "[SkillRule: Perform multiply through; [Typein Skill: Select multiply through]]",
    "question_id": 37897,
    "response": 1,
    "timestamp": 1179506964000
  },
  "116": {
    "concept_id": 116,
    "concept_text": "[SkillRule: Simplify fraction; Reduce fraction]",
    "question_id": 9391,
    "response": 0,
    "timestamp": 1178904691000
  },
  "118": {
    "concept_id": 118,
    "concept_text": "[SkillRule: Perform simplify fraction; [Typein Skill: Simplify fraction]]",
    "question_id": 9392,
    "response": 0,
    "timestamp": 1178904717000
  }
}